hummable/__init__.py
hummable/bledevice.py
hummable/characteristics.py
hummable/scanner.py
hummable-0.1.0.dist-info/WHEEL
hummable-0.1.0.dist-info/METADATA
hummable-0.1.0.dist-info/RECORD
