Metadata-Version: 2.1
Name: hummable
Version: 0.1.0
Summary: Bluetooth BLE for Human Beings
Author: Daniel Fett
Author-email: fett@danielfett.de
Requires-Python: >=3.7,<4.0
Classifier: Programming Language :: Python :: 3
Classifier: Programming Language :: Python :: 3.7
Classifier: Programming Language :: Python :: 3.8
Classifier: Programming Language :: Python :: 3.9
Classifier: Programming Language :: Python :: 3.10
Requires-Dist: bleak (>=0.19.5,<0.20.0)
